odooshow/__init__.py
odooshow/odooshow.py
odooshow-0.6.1.dist-info/METADATA
odooshow-0.6.1.dist-info/WHEEL
odooshow-0.6.1.dist-info/RECORD
