Metadata-Version: 2.3
Name: odooshow
Version: 0.6.1
Summary: Make use of rich power tools to have nice formatted data in Odoo shells
Author: David Vidal
Author-email: chienandalu@gmail.com
Requires-Python: >=3.6.3,<4.0
Classifier: Programming Language :: Python :: 3
Classifier: Programming Language :: Python :: 3.7
Classifier: Programming Language :: Python :: 3.8
Classifier: Programming Language :: Python :: 3.9
Classifier: Programming Language :: Python :: 3.10
Classifier: Programming Language :: Python :: 3.11
Classifier: Programming Language :: Python :: 3.12
Classifier: Programming Language :: Python :: 3.13
Requires-Dist: rich (>=12.5.1,<13.0.0)
